README.md
setup.cfg
setup.py
distributions2021/Binomialdistribution.py
distributions2021/Gaussiandistribution.py
distributions2021/Generaldistribution.py
distributions2021/__init__.py
distributions2021.egg-info/PKG-INFO
distributions2021.egg-info/SOURCES.txt
distributions2021.egg-info/dependency_links.txt
distributions2021.egg-info/not-zip-safe
distributions2021.egg-info/top_level.txt